programgarden_finance/__init__.py
programgarden_finance/ls/__init__.py
programgarden_finance/ls/config.py
programgarden_finance/ls/models.py
programgarden_finance/ls/oauth/__init__.py
programgarden_finance/ls/oauth/generate_token/__init__.py
programgarden_finance/ls/oauth/generate_token/token/__init__.py
programgarden_finance/ls/oauth/generate_token/token/blocks.py
programgarden_finance/ls/oauth/revoke_token/__init__.py
programgarden_finance/ls/oauth/revoke_token/revoke/__init__.py
programgarden_finance/ls/oauth/revoke_token/revoke/blocks.py
programgarden_finance/ls/overseas_futureoption/__init__.py
programgarden_finance/ls/overseas_futureoption/accno/CIDBQ01400/__init__.py
programgarden_finance/ls/overseas_futureoption/accno/CIDBQ01400/blocks.py
programgarden_finance/ls/overseas_futureoption/accno/CIDBQ01500/__init__.py
programgarden_finance/ls/overseas_futureoption/accno/CIDBQ01500/blocks.py
programgarden_finance/ls/overseas_futureoption/accno/CIDBQ01800/__init__.py
programgarden_finance/ls/overseas_futureoption/accno/CIDBQ01800/blocks.py
programgarden_finance/ls/overseas_futureoption/accno/CIDBQ02400/__init__.py
programgarden_finance/ls/overseas_futureoption/accno/CIDBQ02400/blocks.py
programgarden_finance/ls/overseas_futureoption/accno/CIDBQ03000/__init__.py
programgarden_finance/ls/overseas_futureoption/accno/CIDBQ03000/blocks.py
programgarden_finance/ls/overseas_futureoption/accno/CIDBQ05300/__init__.py
programgarden_finance/ls/overseas_futureoption/accno/CIDBQ05300/blocks.py
programgarden_finance/ls/overseas_futureoption/accno/CIDEQ00800/__init__.py
programgarden_finance/ls/overseas_futureoption/accno/CIDEQ00800/blocks.py
programgarden_finance/ls/overseas_futureoption/accno/__init__.py
programgarden_finance/ls/overseas_futureoption/chart/__init__.py
programgarden_finance/ls/overseas_futureoption/chart/o3103/__init__.py
programgarden_finance/ls/overseas_futureoption/chart/o3103/blocks.py
programgarden_finance/ls/overseas_futureoption/chart/o3108/__init__.py
programgarden_finance-0.1.13.dist-info/METADATA
programgarden_finance-0.1.13.dist-info/WHEEL
programgarden_finance-0.1.13.dist-info/RECORD
